README.md
setup.py
PhotoSex/PhotoSex.py
PhotoSex/PhotoSex_config.py
PhotoSex/__init__.py
PhotoSex/basic.py
SimplePhotoSex.egg-info/PKG-INFO
SimplePhotoSex.egg-info/SOURCES.txt
SimplePhotoSex.egg-info/dependency_links.txt
SimplePhotoSex.egg-info/top_level.txt
download_panstar/__init__.py
download_panstar/download_panstar.py
download_panstar/download_panstar_catalog.py
download_panstar/download_panstar_image.py