Metadata-Version: 2.1
Name: SimplePhotoSex
Version: 0.1
Summary: A simple tool to perform aperture or PSF photometry with Sextractor+PSFEX
Home-page: https://gitee.com/zhang-miaomiao1983/photsex
Author: Miaomiao Zhang
Author-email: mmzhang83@163.com
License: MIT
Platform: UNKNOWN
Classifier: Programming Language :: Python :: 3
Classifier: License :: OSI Approved :: MIT License
Classifier: Operating System :: OS Independent
